clearkit/__init__.py
clearkit/test.py
clearkit-0.1.dist-info/LICENSE.txt
clearkit-0.1.dist-info/METADATA
clearkit-0.1.dist-info/WHEEL
clearkit-0.1.dist-info/top_level.txt
clearkit-0.1.dist-info/RECORD
