Metadata-Version: 2.1
Name: clearkit
Version: 0.1
Summary: Complementary code for your programming pleasure
Home-page: https://github.com/ulygit/clearkit
Author: U. Melendez
Author-email: clearkitpy@bfjournal.com
License: UNKNOWN
Project-URL: Bug Tracker, https://github.com/ulygit/clearkit/issues
Platform: UNKNOWN
Classifier: Programming Language :: Python :: 3
Classifier: License :: OSI Approved :: MIT License
Classifier: Operating System :: OS Independent
Requires-Python: >=3.9
License-File: LICENSE.txt
